tests/fixtures/__init__.py
tests/fixtures/stride_result_fixture.py
tests/fixtures/test_main_context_fixture.py
tests/helpers/__init__.py
tests/helpers/convert_year_month_array_to_datetime.py
tests/helpers/flight_series_dataset.py
tests/helpers/flights_dataset.py
time_series_dataset_generator/__init__.py
time_series_dataset_generator/time_series_dataset_generator.py
time_series_dataset_generator-0.1.10.dist-info/LICENSE
time_series_dataset_generator-0.1.10.dist-info/METADATA
time_series_dataset_generator-0.1.10.dist-info/WHEEL
time_series_dataset_generator-0.1.10.dist-info/top_level.txt
time_series_dataset_generator-0.1.10.dist-info/RECORD
