Metadata-Version: 2.1
Name: time-series-dataset-generator
Version: 0.1.10
Summary: Generator for time-series-dataset.
Home-page: https://github.com/krypton-unite/time_series_dataset_generator.git
Author: Daniel Kaminski de Souza
Author-email: daniel@kryptonunite.com
License: The Unlicense
Download-URL: https://pypi.org/project/time-series-dataset-generator/
Keywords: Time series dataset generator
Platform: UNKNOWN
Requires-Python: >=3.7
Requires-Dist: time-series-dataset
Requires-Dist: time-series-generator
Requires-Dist: pandas
Requires-Dist: sklearn
Provides-Extra: dev
Requires-Dist: bumpversion ; extra == 'dev'
Requires-Dist: twine ; extra == 'dev'
Requires-Dist: wheel ; extra == 'dev'
Requires-Dist: pylint ; extra == 'dev'
Requires-Dist: autopep8 ; extra == 'dev'
Provides-Extra: docs
Provides-Extra: test
Requires-Dist: pytest ; extra == 'test'
Requires-Dist: pytest-cov ; extra == 'test'
Requires-Dist: seaborn ; extra == 'test'
Requires-Dist: time-series-predictor ; extra == 'test'
Requires-Dist: time-series-models ; extra == 'test'
